<?xml version="1.0" encoding="utf-8"?>
<LanguageData>
  <Nudist.degreeDatas.nudist.label>Nudist</Nudist.degreeDatas.nudist.label>
  <Nudist.degreeDatas.nudist.description>{PAWN_nameDef} you will not only open mind free to enjoy those. {PAWN_pronoun} wear it, you will be more than satisfied. </Nudist.degreeDatas.nudist.description>
  <Bloodlust.degreeDatas.bloodlust.label>good choice of shedding blood</Bloodlust.degreeDatas.bloodlust.label>
  <Bloodlust.degreeDatas.bloodlust.description>{PAWN_nameDef} blood as well, many people were wounded and died. ppayai about four times greater than other {PAWN_pronoun} discussed. </Bloodlust.degreeDatas.bloodlust.description>
  <Kind.degreeDatas.kind.label>Good people</Kind.degreeDatas.kind.label>
  <Kind.degreeDatas.kind.description>Home {PAWN_nameDef} good. {PAWN_pronoun} always for all in the mind, not other low-light quality. </Kind.degreeDatas.kind.description>
  <Psychopath.degreeDatas.psychopath.label>difference</Psychopath.degreeDatas.psychopath.label>
  <Psychopath.degreeDatas.psychopath.description>{PAWN_nameDef} can not imagine things, make up the feelings of others snuggled. Others do not suffer hardship, but {PAWN_objective}. Other, dismantled or in jail or dead areas or a complete defeat, but we will try to sell or slave, only {PAWN_pronoun} still be poor. {PAWN_pronoun} not get the "feel" of that socialization is. </Psychopath.degreeDatas.psychopath.description>
  <Cannibal.degreeDatas.cannibal.label>kannibalism priority</Cannibal.degreeDatas.cannibal.label>
  <Cannibal.degreeDatas.cannibal.description>{PAWN_nameDef} cannibal, and you know that a terrible wrong. In the past, the last more than one day, and now ... {PAWN_pronoun} try. </Cannibal.degreeDatas.cannibal.description>
  <Abrasive.degreeDatas.abrasive.label>disorders</Abrasive.degreeDatas.abrasive.label>
  <Abrasive.degreeDatas.abrasive.description>{PAWN_nameDef} moon is always in the hands of the senses, especially when frustrated, rather drawings the wrong way rub. </Abrasive.degreeDatas.abrasive.description>
  <TooSmart.degreeDatas.too_smart.label>Unuboreya</TooSmart.degreeDatas.too_smart.label>
  <TooSmart.degreeDatas.too_smart.description>{PAWN_nameDef} more than talent, and I think you're smart. {PAWN_pronoun}, but also to learn faster than others in something completely random. </TooSmart.degreeDatas.too_smart.description>
  <Brawler.degreeDatas.brawler.label>warrior</Brawler.degreeDatas.brawler.label>
  <Brawler.degreeDatas.brawler.description>{PAWN_nameDef} after a fight or war. Mortar guns, when people are very nervous to hand combat is too high, short-{PAWN_possessive} hand. </Brawler.degreeDatas.brawler.description>
  <Masochist.degreeDatas.masochist.label>masochist</Masochist.degreeDatas.masochist.label>
  <Masochist.degreeDatas.masochist.description>{PAWN_nameDef}, that is, taking a good fun day. I {PAWN_pronoun} know why, but not eccentric. </Masochist.degreeDatas.masochist.description>
  <NightOwl.degreeDatas.night_owl.label>Couriers</NightOwl.degreeDatas.night_owl.label>
  <NightOwl.degreeDatas.night_owl.description>{PAWN_nameDef} in the middle of the night, I sleep during the day.\n\n{PAWN_pronoun} workers, but in the night time (23:00 -06) and wakes up bonuses 'value', but wakes up out in the morning (11:00 -18), prime minister and "feel".\n\nNot {PAWN_pronoun} negative trait "emotions" left in the dark. </NightOwl.degreeDatas.night_owl.description>
  <Greedy.degreeDatas.greedy.label>incapacity</Greedy.degreeDatas.greedy.label>
  <Greedy.degreeDatas.greedy.description>{PAWN_nameDef}'re looking bedroom is a real luxury. {PAWN_pronoun}, while demanding a voice {PAWN_pronoun} bad "feeling". </Greedy.degreeDatas.greedy.description>
  <Jealous.degreeDatas.jealous.label>Jealous</Jealous.degreeDatas.jealous.label>
  <Jealous.degreeDatas.jealous.description>Bring to room {PAWN_nameDef} paler than others that also affect self-esteem. {PAWN_pronoun} while other luxury rooms of their "feelings" would be even worse. </Jealous.degreeDatas.jealous.description>
  <Ascetic.degreeDatas.ascetic.label>Withdrawal</Ascetic.degreeDatas.ascetic.label>
  <Ascetic.degreeDatas.ascetic.description>Many {PAWN_nameDef} monastery life. {PAWN_pronoun} and as a company, but {PAWN_pronoun}. {PAWN_pronoun} and "slave" are at a loss, and they eat raw. </Ascetic.degreeDatas.ascetic.description>
  <Gay.degreeDatas.gay.label>homosexuals</Gay.degreeDatas.gay.label>
  <Gay.degreeDatas.gay.description>Interested {PAWN_nameDef} of the same sex romantic attraction to the meaning. </Gay.degreeDatas.gay.description>
  <AnnoyingVoice.degreeDatas.annoying_voice.label>Spoke the word</AnnoyingVoice.degreeDatas.annoying_voice.label>
  <AnnoyingVoice.degreeDatas.annoying_voice.description>{PAWN_nameDef} the efficiency is bad, then you usually express about shaping bound and uncertain cough turns people talking. This makes it easier for others to {PAWN_objective} hatred. </AnnoyingVoice.degreeDatas.annoying_voice.description>
  <CreepyBreathing.degreeDatas.creepy_breathing.label>bad breath</CreepyBreathing.degreeDatas.creepy_breathing.label>
  <CreepyBreathing.degreeDatas.creepy_breathing.description>Violence, {PAWN_nameDef} sweating all the time, what people want kimiwaru. </CreepyBreathing.degreeDatas.creepy_breathing.description>
  <Pyromaniac.degreeDatas.pyromaniac.label>arsonist</Pyromaniac.degreeDatas.pyromaniac.label>
  <Pyromaniac.degreeDatas.pyromaniac.description>It {PAWN_nameDef} the fire of love. do the extinguishing of the fire, not {PAWN_pronoun}. The problem, {PAWN_pronoun}, now you continue to break the Teatarishidai. {PAWN_possessive} and a "movement" is likely to land. </Pyromaniac.degreeDatas.pyromaniac.description>
  <Wimp.degreeDatas.wimp.label>funky</Wimp.degreeDatas.wimp.label>
  <Wimp.degreeDatas.wimp.description>{PAWN_nameDef} wimp embarrassed story told. Moreover, a little sick, and he will be locked in the car. </Wimp.degreeDatas.wimp.description>
  <Nimble.degreeDatas.nimble.label>Making supple body</Nimble.degreeDatas.nimble.label>
  <Nimble.degreeDatas.nimble.description>Certain sporting {PAWN_nameDef} owner. {PAWN_pronoun} grace unusual and looks like a dance, and even dangerous. </Nimble.degreeDatas.nimble.description>
  <FastLearner.degreeDatas.fast_learner.label>soon monooboe</FastLearner.degreeDatas.fast_learner.label>
  <FastLearner.degreeDatas.fast_learner.description>{PAWN_nameDef} is monooboe tip. in my {PAWN_pronoun} things harder than others. </FastLearner.degreeDatas.fast_learner.description>
  <Undergrounder.degreeDatas.undergrounder.label>Underworld</Undergrounder.degreeDatas.undergrounder.label>
  <Undergrounder.degreeDatas.undergrounder.description>{PAWN_nameDef} not have the experience of external light. {PAWN_pronoun}, or full or {PAWN_pronoun} not care, because I feel like if you do not have to worry about the dark fever is not limited sense. </Undergrounder.degreeDatas.undergrounder.description>
  <!-- The below really probably should've been spectrum traits -->
  <Transhumanist.degreeDatas.transhumanist.label>Gita</Transhumanist.degreeDatas.transhumanist.label>
  <Transhumanist.degreeDatas.transhumanist.description>{PAWN_nameDef} I think that the weak limit of the human body. {PAWN_pronoun} themselves often guitar. </Transhumanist.degreeDatas.transhumanist.description>
  <BodyPurist.degreeDatas.body_purist.label>Natural standing theory</BodyPurist.degreeDatas.body_purist.label>
  <BodyPurist.degreeDatas.body_purist.description>{PAWN_nameDef} reasons to believe that there is a limit to the chest, there is. {PAWN_pronoun}, taking into account need for his disgusting gitai reduced. </BodyPurist.degreeDatas.body_purist.description>
  <DislikesMen.degreeDatas.misandrist.label>Oh, actually support</DislikesMen.degreeDatas.misandrist.label>
  <DislikesMen.degreeDatas.misandrist.description>{PAWN_nameDef} will not be easy to otokogirai. </DislikesMen.degreeDatas.misandrist.description>
  <DislikesWomen.degreeDatas.misogynist.label>hate</DislikesWomen.degreeDatas.misogynist.label>
  <DislikesWomen.degreeDatas.misogynist.description>{PAWN_nameDef} misogyny distrust of all women. </DislikesWomen.degreeDatas.misogynist.description>
  <GreatMemory.degreeDatas.great_memory.label>Ultra memory</GreatMemory.degreeDatas.great_memory.label>
  <GreatMemory.degreeDatas.great_memory.description>They {PAWN_nameDef} amazing memory. {PAWN_pronoun} the speed at which we can say about art that do not use half-forgotten now. </GreatMemory.degreeDatas.great_memory.description>
  <Tough.degreeDatas.tough.label>sturdy</Tough.degreeDatas.tough.label>
  <Tough.degreeDatas.tough.description>{PAWN_nameDef} thick skin, the owner physically fat boneless. although there are no other victims {PAWN_pronoun}, same beat. </Tough.degreeDatas.tough.description>
  <Gourmand.degreeDatas.gourmand.label>Gilead Doraku</Gourmand.degreeDatas.gourmand.label>
  <Gourmand.degreeDatas.gourmand.description>{PAWN_nameDef} life around food. {PAWN_pronoun} hungry, though, of course, sometimes voracious appetite for power and hunger attacks easily. </Gourmand.degreeDatas.gourmand.description>
  <QuickSleeper.degreeDatas.quick_sleeper.label>Master deep sleep</QuickSleeper.degreeDatas.quick_sleeper.label>
  <QuickSleeper.degreeDatas.quick_sleeper.description>{PAWN_nameDef} that you need less sleep than the average person. {PAWN_pronoun} bed area, a completely different take on the right, {PAWN_pronoun}, you can get plenty of rest 2/3 hour. </QuickSleeper.degreeDatas.quick_sleeper.description>
</LanguageData>
